Metadata-Version: 2.1
Name: pacoteparatestedio
Version: 0.0.1
Summary: My short description
Home-page: https://github.com/thaiisfaustino
Author: Thais
Author-email: thaisfsouza@outlook.com
Requires-Python: >=3.8
